LICENSE
MANIFEST.in
README.md
setup.cfg
setup.py
karma_sphinx_theme/__init__.py
karma_sphinx_theme/_version.py
karma_sphinx_theme/breadcrumbs.html
karma_sphinx_theme/layout.html
karma_sphinx_theme/search.html
karma_sphinx_theme/searchbox.html
karma_sphinx_theme/theme.conf
karma_sphinx_theme.egg-info/PKG-INFO
karma_sphinx_theme.egg-info/SOURCES.txt
karma_sphinx_theme.egg-info/dependency_links.txt
karma_sphinx_theme.egg-info/entry_points.txt
karma_sphinx_theme.egg-info/top_level.txt
karma_sphinx_theme/static/css/custom.css
karma_sphinx_theme/static/css/custom.css.map
karma_sphinx_theme/static/css/theme.css
karma_sphinx_theme/static/css/theme.css.map
karma_sphinx_theme/static/css/theme.min.css
karma_sphinx_theme/static/css/theme.min.css.map
karma_sphinx_theme/static/font/fontello.eot
karma_sphinx_theme/static/font/fontello.svg
karma_sphinx_theme/static/font/fontello.ttf
karma_sphinx_theme/static/font/fontello.woff
karma_sphinx_theme/static/font/fontello.woff2
karma_sphinx_theme/static/js/theme.js