Metadata-Version: 1.0
Name: karma-sphinx-theme
Version: 0.0.6
Summary: A sphinx theme built with KarmaCSS
Home-page: https://karma_sphinx_theme.readthedocs.io
Author: Stuart George
Author-email: stuart@accentdesign.co.uk
License: UNKNOWN
Platform: UNKNOWN
